komon/__init__.py
komon/analyzer.py
komon/cli.py
komon/contextual_advisor.py
komon/disk_predictor.py
komon/duplicate_detector.py
komon/formatters.py
komon/history.py
komon/log_analyzer.py
komon/log_tail_extractor.py
komon/log_trends.py
komon/log_watcher.py
komon/long_running_detector.py
komon/monitor.py
komon/notification.py
komon/notification_history.py
komon/os_detection.py
komon/progressive_message.py
komon/report_formatter.py
komon/settings_validator.py
komon/webhook_notifier.py
komon/weekly_data.py
komon/commands/__init__.py
komon/commands/advise.py
komon/commands/guide.py
komon/commands/initial.py
komon/commands/status.py
komon/net/__init__.py
komon/net/http_check.py
komon/net/ping_check.py
komon/net/state_manager.py
komon-1.27.0.data/data/config/settings.yml.sample
komon-1.27.0.dist-info/LICENSE
komon-1.27.0.dist-info/METADATA
komon-1.27.0.dist-info/WHEEL
komon-1.27.0.dist-info/entry_points.txt
komon-1.27.0.dist-info/top_level.txt
komon-1.27.0.dist-info/RECORD
