Metadata-Version: 2.1
Name: komon
Version: 1.27.0
Summary: 軽量アドバイザー型SOAR風監視ツール
Home-page: https://github.com/kamonabe/Komon
Author: kamonabe
Author-email: kamonabe1927@gmail.com
License: UNKNOWN
Platform: UNKNOWN
Classifier: Development Status :: 4 - Beta
Classifier: Intended Audience :: Developers
Classifier: Intended Audience :: System Administrators
Classifier: License :: OSI Approved :: MIT License
Classifier: Programming Language :: Python :: 3
Classifier: Programming Language :: Python :: 3.10
Classifier: Programming Language :: Python :: 3.11
Classifier: Programming Language :: Python :: 3.12
Classifier: Operating System :: POSIX :: Linux
Classifier: Topic :: System :: Monitoring
Requires-Python: >=3.10
License-File: LICENSE
Requires-Dist: psutil>=5.9.0
Requires-Dist: PyYAML>=6.0
Requires-Dist: requests>=2.31.0
